LICENSE
pyzscaler/__init__.py
pyzscaler/utils.py
pyzscaler/zcc/__init__.py
pyzscaler/zcc/devices.py
pyzscaler/zcc/secrets.py
pyzscaler/zcc/session.py
pyzscaler/zcon/__init__.py
pyzscaler/zcon/admin.py
pyzscaler/zcon/config.py
pyzscaler/zcon/connectors.py
pyzscaler/zcon/locations.py
pyzscaler/zcon/session.py
pyzscaler/zdx/__init__.py
pyzscaler/zdx/admin.py
pyzscaler/zdx/apps.py
pyzscaler/zdx/devices.py
pyzscaler/zdx/session.py
pyzscaler/zdx/users.py
pyzscaler/zia/__init__.py
pyzscaler/zia/admin_and_role_management.py
pyzscaler/zia/apptotal.py
pyzscaler/zia/audit_logs.py
pyzscaler/zia/cloud_apps.py
pyzscaler/zia/config.py
pyzscaler/zia/dlp.py
pyzscaler/zia/firewall.py
pyzscaler/zia/labels.py
pyzscaler/zia/locations.py
pyzscaler/zia/sandbox.py
pyzscaler/zia/security.py
pyzscaler/zia/session.py
pyzscaler/zia/ssl_inspection.py
pyzscaler/zia/traffic.py
pyzscaler/zia/url_categories.py
pyzscaler/zia/url_filters.py
pyzscaler/zia/users.py
pyzscaler/zia/vips.py
pyzscaler/zia/web_dlp.py
pyzscaler/zpa/__init__.py
pyzscaler/zpa/app_segments.py
pyzscaler/zpa/certificates.py
pyzscaler/zpa/cloud_connector_groups.py
pyzscaler/zpa/connectors.py
pyzscaler/zpa/idp.py
pyzscaler/zpa/inspection.py
pyzscaler/zpa/lss.py
pyzscaler/zpa/machine_groups.py
pyzscaler/zpa/policies.py
pyzscaler/zpa/posture_profiles.py
pyzscaler/zpa/provisioning.py
pyzscaler/zpa/saml_attributes.py
pyzscaler/zpa/scim_attributes.py
pyzscaler/zpa/scim_groups.py
pyzscaler/zpa/segment_groups.py
pyzscaler/zpa/server_groups.py
pyzscaler/zpa/servers.py
pyzscaler/zpa/service_edges.py
pyzscaler/zpa/session.py
pyzscaler/zpa/trusted_networks.py
pyzscaler-1.6.0.dist-info/LICENSE
pyzscaler-1.6.0.dist-info/METADATA
pyzscaler-1.6.0.dist-info/WHEEL
pyzscaler-1.6.0.dist-info/RECORD
