Metadata-Version: 2.1
Name: pyzscaler
Version: 1.6.0
Summary: A python SDK for the Zscaler API.
Home-page: https://pyzscaler.packet.tech/
License: MIT
Author: Mitch Kelly
Author-email: me@mkelly.dev
Requires-Python: >=3.8,<4.0
Classifier: Environment :: Console
Classifier: Intended Audience :: Developers
Classifier: Intended Audience :: Information Technology
Classifier: Intended Audience :: System Administrators
Classifier: License :: OSI Approved :: MIT License
Classifier: Natural Language :: English
Classifier: Programming Language :: Python :: 3
Classifier: Programming Language :: Python :: 3.8
Classifier: Programming Language :: Python :: 3.9
Classifier: Programming Language :: Python :: 3.10
Classifier: Programming Language :: Python :: 3.11
Classifier: Programming Language :: Python :: 3.12
Classifier: Topic :: Security
Classifier: Topic :: Software Development :: Libraries :: Python Modules
Requires-Dist: python-box (==7.0.1)
Requires-Dist: restfly (==1.4.7)
Project-URL: Bug Tracker, https://github.com/mitchos/pyZscaler/issues
Project-URL: Documentation, https://pyzscaler.readthedocs.io/
Project-URL: Repository, https://github.com/mitchos/pyZscaler
